{"id":"633c38c4c606e149acf10136","width":360,"height":504,"path":"background.jpeg","matrix":"3.0,0.0,0.0,0.0,3.0,120.99999,0.0,0.0,1.0","sticker":[{"opacity":255,"opacity_border":255,"color_border":0,"size_border":20,"type":"drawable","path":"drawable1665935733139.png","matrix":"1.4649161,0.0,-312.4329,0.0,1.6602979,35.488052,0.0,0.0,1.0","color_fill":0,"isLock":false,"width":1600,"height":1067,"rotate":0},{"opacity":255,"opacity_border":255,"color_border":0,"size_border":20,"type":"drawable","path":"drawable1665935733331.png","matrix":"2.4211884,0.0,-299.4206,0.0,2.4211884,-242.04277,0.0,0.0,1.0","color_fill":0,"isLock":false,"width":1078,"height":1080,"rotate":0},{"type":"text","matrix":"3.0,0.0,302.15454,0.0,3.0,250.47923,0.0,0.0,1.0","width":155,"height":104,"rotate":0,"content":"NEW\nYEAR","sizePx":59,"fontPosition":-1,"fontName":"Tenor Sans","alignment":2,"isLower":false,"isBold":false,"isUnderline":false,"isItalic":false,"spacing":0,"lineHeight":20,"textOpacity":255,"colorShadow":0,"blurShadow":80,"offsetX":10,"offsetY":5,"shadowPosition":0,"borderPosition":0,"colorBorder":0,"sizeBorder":5,"backgroundOpacity":255,"paddingBackgroundX":0,"paddingBackgroundY":0,"roundBackground":0,"curve":0,"gradientPosition":0,"angleGradientText":0,"palettePosition":0,"colorText":-552650,"colorPosition":0,"colorBackgroundPosition":0,"colorBackground":0,"gradientBackgroundPosition":0,"angleGradientBackground":90,"colorBorderBackground":0,"colorBorderBackgroundPosition":0,"borderBackgroundOpacity":255,"sizeBorderBackground":3,"isLock":false},{"type":"text","matrix":"2.9805853,0.34075102,289.65652,-0.34075102,2.9805853,609.66095,0.0,0.0,1.0","width":195,"height":62,"rotate":0,"content":"FAIR\n","sizePx":64,"fontPosition":-1,"fontName":"Charmonman","alignment":2,"isLower":false,"isBold":false,"isUnderline":false,"isItalic":false,"spacing":0,"lineHeight":20,"textOpacity":255,"colorShadow":0,"blurShadow":80,"offsetX":10,"offsetY":5,"shadowPosition":0,"borderPosition":0,"colorBorder":0,"sizeBorder":5,"backgroundOpacity":255,"paddingBackgroundX":0,"paddingBackgroundY":0,"roundBackground":0,"curve":0,"gradientPosition":0,"angleGradientText":0,"palettePosition":0,"colorText":-1,"colorPosition":6,"colorBackgroundPosition":0,"colorBackground":0,"gradientBackgroundPosition":0,"angleGradientBackground":90,"colorBorderBackground":0,"colorBorderBackgroundPosition":0,"borderBackgroundOpacity":255,"sizeBorderBackground":3,"isLock":false},{"type":"text","matrix":"3.0,0.0,820.8864,0.0,3.0,275.37,0.0,0.0,1.0","width":46,"height":32,"rotate":0,"content":"DEC 20 -\nJAN 31\n","sizePx":13,"fontPosition":-1,"fontName":"Open Sans","alignment":3,"isLower":false,"isBold":true,"isUnderline":false,"isItalic":false,"spacing":0,"lineHeight":12.400001525878906,"textOpacity":255,"colorShadow":0,"blurShadow":80,"offsetX":10,"offsetY":5,"shadowPosition":0,"borderPosition":0,"colorBorder":0,"sizeBorder":5,"backgroundOpacity":255,"paddingBackgroundX":0,"paddingBackgroundY":0,"roundBackground":0,"curve":0,"gradientPosition":0,"angleGradientText":0,"palettePosition":0,"colorText":-1,"colorPosition":6,"colorBackgroundPosition":0,"colorBackground":0,"gradientBackgroundPosition":0,"angleGradientBackground":90,"colorBorderBackground":0,"colorBorderBackgroundPosition":0,"borderBackgroundOpacity":255,"sizeBorderBackground":3,"isLock":false},{"type":"text","matrix":"3.0,0.0,97.76107,0.0,3.0,323.5664,0.0,0.0,1.0","width":24,"height":20,"rotate":0,"content":"YOUR\nNAME","sizePx":9,"fontPosition":-1,"fontName":"Open Sans","alignment":1,"isLower":false,"isBold":true,"isUnderline":false,"isItalic":false,"spacing":0,"lineHeight":6.399999618530273,"textOpacity":255,"colorShadow":0,"blurShadow":80,"offsetX":10,"offsetY":5,"shadowPosition":0,"borderPosition":0,"colorBorder":0,"sizeBorder":5,"backgroundOpacity":255,"paddingBackgroundX":0,"paddingBackgroundY":0,"roundBackground":0,"curve":0,"gradientPosition":0,"angleGradientText":0,"palettePosition":0,"colorText":-1,"colorPosition":6,"colorBackgroundPosition":0,"colorBackground":0,"gradientBackgroundPosition":0,"angleGradientBackground":90,"colorBorderBackground":0,"colorBorderBackgroundPosition":0,"borderBackgroundOpacity":255,"sizeBorderBackground":3,"isLock":false},{"type":"text","matrix":"3.0,0.0,358.30652,0.0,3.0,847.8248,0.0,0.0,1.0","width":116,"height":31,"rotate":0,"content":"Show this invitation\nand get a free gift\n","sizePx":13,"fontPosition":-1,"fontName":"Open Sans","alignment":2,"isLower":true,"isBold":false,"isUnderline":false,"isItalic":false,"spacing":0,"lineHeight":11.200000762939453,"textOpacity":255,"colorShadow":0,"blurShadow":80,"offsetX":10,"offsetY":5,"shadowPosition":0,"borderPosition":0,"colorBorder":0,"sizeBorder":5,"backgroundOpacity":255,"paddingBackgroundX":0,"paddingBackgroundY":0,"roundBackground":0,"curve":0,"gradientPosition":0,"angleGradientText":0,"palettePosition":0,"colorText":-1,"colorPosition":6,"colorBackgroundPosition":0,"colorBackground":0,"gradientBackgroundPosition":0,"angleGradientBackground":90,"colorBorderBackground":0,"colorBorderBackgroundPosition":0,"borderBackgroundOpacity":255,"sizeBorderBackground":3,"isLock":false},{"opacity":255,"opacity_border":255,"color_border":0,"size_border":20,"type":"drawable","path":"drawable1665935733513.png","matrix":"3.0217066,0.0,769.54565,0.0,3.0217066,1345.0464,0.0,0.0,1.0","color_fill":-1,"isLock":false,"width":67,"height":67,"rotate":0},{"opacity":255,"opacity_border":255,"color_border":0,"size_border":20,"type":"drawable","path":"drawable1665935733514.png","matrix":"0.05888818,0.0,97.500015,0.0,0.05883231,237.24995,0.0,0.0,1.0","color_fill":-1,"isLock":false,"width":1053,"height":1080,"rotate":0},{"opacity":255,"opacity_border":255,"color_border":0,"size_border":20,"type":"drawable","path":"drawable1665935733550.png","matrix":"0.1705424,0.0,794.4551,0.0,0.17073339,1370.0411,0.0,0.0,1.0","color_fill":0,"isLock":false,"width":895,"height":893,"rotate":0},{"type":"shape","matrix":"1.557121,0.0,120.54027,0.0,0.35453433,408.59998,0.0,0.0,1.0","width":540,"height":540,"rotate":0,"opacity":255,"color":0,"opacity_border":255,"color_border":-618187,"size_border":4,"shape_type":"CIRCLE_STROKE"}],"ext":{"en":["new year","holiday","celebration","celebrate","event","festive","newyear","winter","fair","tree","city","town","houses","buildings","cute","night","eve","snow","cozy","invitation"]}}